vega_admin/__init__.py
vega_admin/apps.py
vega_admin/crispy_utils.py
vega_admin/forms.py
vega_admin/mixins.py
vega_admin/models.py
vega_admin/settings.py
vega_admin/utils.py
vega_admin/views.py
vega_admin/widgets.py
vega_admin/contrib/__init__.py
vega_admin/contrib/users/__init__.py
vega_admin/contrib/users/apps.py
vega_admin/contrib/users/forms.py
vega_admin/contrib/users/models.py
vega_admin/contrib/users/urls.py
vega_admin/contrib/users/views.py
vega_admin/static/badmin/bootstrap/css/bootstrap-theme.css
vega_admin/static/badmin/bootstrap/css/bootstrap-theme.css.map
vega_admin/static/badmin/bootstrap/css/bootstrap-theme.min.css
vega_admin/static/badmin/bootstrap/css/bootstrap-theme.min.css.map
vega_admin/static/badmin/bootstrap/css/bootstrap.css
vega_admin/static/badmin/bootstrap/css/bootstrap.css.map
vega_admin/static/badmin/bootstrap/css/bootstrap.min.css
vega_admin/static/badmin/bootstrap/css/bootstrap.min.css.map
vega_admin/static/badmin/bootstrap/fonts/glyphicons-halflings-regular.eot
vega_admin/static/badmin/bootstrap/fonts/glyphicons-halflings-regular.svg
vega_admin/static/badmin/bootstrap/fonts/glyphicons-halflings-regular.ttf
vega_admin/static/badmin/bootstrap/fonts/glyphicons-halflings-regular.woff
vega_admin/static/badmin/bootstrap/fonts/glyphicons-halflings-regular.woff2
vega_admin/static/badmin/bootstrap/js/bootstrap.js
vega_admin/static/badmin/bootstrap/js/bootstrap.min.js
vega_admin/static/badmin/bootstrap/js/npm.js
vega_admin/static/badmin/css/buttons.css
vega_admin/static/badmin/css/forms.css
vega_admin/static/badmin/css/styles.css
vega_admin/static/badmin/js/custom.js
vega_admin/static/badmin/js/ie10-viewport-bug-workaround.js
vega_admin/static/badmin/js/jquery-2.2.4.min.js
vega_admin/templates/vega_admin/badmin/base.html
vega_admin/templates/vega_admin/badmin/create.html
vega_admin/templates/vega_admin/badmin/delete.html
vega_admin/templates/vega_admin/badmin/list.html
vega_admin/templates/vega_admin/badmin/read.html
django_vega_admin-0.0.19.dist-info/LICENSE
django_vega_admin-0.0.19.dist-info/METADATA
django_vega_admin-0.0.19.dist-info/WHEEL
django_vega_admin-0.0.19.dist-info/top_level.txt
django_vega_admin-0.0.19.dist-info/RECORD
