Metadata-Version: 2.1
Name: django-vega-admin
Version: 0.0.19
Summary: Simple and fast automated CRUD for any Django model
Home-page: https://github.com/moshthepitt/django-vega-admin
Author: Kelvin Jayanoris
Author-email: kelvin@jayanoris.com
License: MIT
Platform: UNKNOWN
Classifier: Programming Language :: Python
Classifier: Programming Language :: Python :: 3.6
Classifier: Programming Language :: Python :: 3.7
Classifier: Programming Language :: Python :: 3.8
Classifier: Framework :: Django
Classifier: Framework :: Django :: 2.2
Classifier: Framework :: Django :: 3.0
Requires-Dist: Django (>=2.2)
Requires-Dist: django-crispy-forms
Requires-Dist: django-braces
Requires-Dist: django-filter
Requires-Dist: django-tables2
Requires-Dist: tablib
Requires-Dist: pyyaml (>=4.2b1)
